Metadata-Version: 1.0
Name: proto-distributions
Version: 0.1
Summary: Probability distributions
Home-page: UNKNOWN
Author: Emefiele-Konyeri Awinrin
Author-email: awinrin4bless@gmail.com
License: UNKNOWN
Platform: UNKNOWN
